Workbook

Sheet srpski
B1: BCS | C1: ID | D1: literals | E1: def | F1: usage | G1: hypernymID | H1: hypernym_literals | I1: hypernym_def | J1: hypernym_usage
A2: medicine | B2: NULL | C2: ENG30-06045562-n | D2: medicina; medicinske nauke | E2: Nauka koja se bavi održvanjem zdravlja, prevencijom i lečenjem bolesti. | F2: - | G2: ENG30-06037298-n | H2: nauka o živim bićima | I2: Bilo koja od grana prirodnih nauka koja se bavi strukturom i ponašanjem živih organizama. | J2: -
A3: medicine | B3: NULL | C3: ENG30-14298815-n | D3: rana; ozleda | E3: Bilo koja pukotina na koži ili organu izazvana nasilno ili hirurškim zahvatom. | F3: - | G3: ENG30-14285662-n | H3: povreda; ozleda | I3: Bilo kakva oštetočina na telu izazvana nasiljem, nezgodom ili prelomom. | J3: -
A4: medicine | B4: NULL | C4: ENG30-00086320-v | D4: ubrizgati; ušpricati | E4: Dati injekciju. | F4: - | G4: ENG30-00081072-v | H4: dati; propisati | I4: Davati ili primenjivati; o lekovima. | J4: -
A5: medicine | B5: NULL | C5: ENG30-09784306-n | D5: alergolog | E5: Lekar koji je obučn za dijagnostikovanje i lečenje alergija. | F5: 1 : Precizna dijagnoza uključuje više stručnjaka, alergologa, specijaliste za uho, grlo i nos i pulmologa. | G5: ENG30-10020890-n | H5: lekar; lečnik; doktor | I5: Medicinski radnik sa dozvolom. | J5: -
A6: medicine | B6: NULL | C6: ENG30-10126009-n | D6: lekar opšte prakse; lekar opšte medicine | E6: Lekar koji nije specijalista za neku određenu bolest, već leči sve bolesti. | F6: 1 : Nisu retki lekari opšte medicine zaposleni u domovima zdravlja koji tvrde da bar svaki drugi pacijent koji im doše ima povišen krvni pritisak. | 2 : U ordinacijama lekara opšte prakse pacijenti se sve češće upuštaju u ubeđivanja o potrebi da dobiju uput za neki pregled. | G6: ENG30-10020890-n | H6: lekar; lečnik; doktor | I6: Medicinski radnik sa dozvolom. | J6: -
A7: medicine | B7: NULL | C7: ENG30-10077278-n | D7: porodični lekar; kućni lekar | E7: Lekar opšte prakse koji leči sve članove porodice. | F7: 1 : Porodični lekar leči celog čoveka, a ne samo njegovu bolest. | 2 : Primadona nije htela, posle pauze, da izađe iz garderobe nego je, ridajući, tražila da hitno dovedu njene roditelje i kućnog lekara. | G7: ENG30-10126009-n | H7: lekar opšte prakse; lekar opšte medicine | I7: Lekar koji nije specijalista za neku određenu bolest, već leči sve bolesti. | J7: 1 : Nisu retki lekari opšte medicine zaposleni u domovima zdravlja koji tvrde da bar svaki drugi pacijent koji im doše ima povišen krvni pritisak. | 2 : U ordinacijama lekara opšte prakse pacijenti se sve češće upuštaju u ubeđivanja o potrebi da dobiju uput za neki pregled.
A8: medicine | B8: NULL | C8: ENG30-09970493-n | D8: seoski lekar | E8: Lekar koji obavlja praksu na selu, a ne u gradu, i bično dalje od udaljenih modernih bolnica. | F8: 1 : Seoski lekar stigao iz Beograda, V. D, odlučila da se nastani u selu nadomak Užica, gde joj je dat novi stan. | G8: ENG30-10126009-n | H8: lekar opšte prakse; lekar opšte medicine | I8: Lekar koji nije specijalista za neku određenu bolest, već leči sve bolesti. | J8: 1 : Nisu retki lekari opšte medicine zaposleni u domovima zdravlja koji tvrde da bar svaki drugi pacijent koji im doše ima povišen krvni pritisak. | 2 : U ordinacijama lekara opšte prakse pacijenti se sve češće upuštaju u ubeđivanja o potrebi da dobiju uput za neki pregled.
A9: medicine | B9: NULL | C9: ENG30-10211203-n | D9: stažista | E9: Lekar početnik, ili apsolvent medicine, koji radi kao lekar pod nadzorom starijih lekara. | F9: 1 : Neki rođak nas je upoznao... doktorka, stažista, mlada zgodna raspuštenica... i tako. | G9: ENG30-10020890-n | H9: lekar; lečnik; doktor | I9: Medicinski radnik sa dozvolom. | J9: -
A10: medicine | B10: NULL | C10: ENG30-10632576-n | D10: lekar specijalista | E10: Lekar koji je specijalizirao neku granu medicine. | F10: 1 : Tom prilikom ga je pregledao lekar specijalista i propisao mu odgovarajuću terapiju. | G10: ENG30-10020890-n | H10: lekar; lečnik; doktor | I10: Medicinski radnik sa dozvolom. | J10: -
A11: medicine | B11: NULL | C11: ENG30-10059323-n | D11: specijalista ORL; specijalista za uvo, grlo i nos; otorinolaringolog; otorhinolaryngologist; rhinolaryngologist | E11: Specijalista za bolesti uva, grla i nosa. | F11: 1 : Mada su zbog kašlja, temperature i bolova u grlu mnogi ovih dana pomoć zatražili kod otorinolaringologa ili lekara opšte prakse, epidemiolozi tvrde da za gužve u domovima zdravlja krivac nije virus gripa. | 2 : dr Snežana B., specijalista ORL | 3 : Specijalisti za uvo, grlo i nos su Nosović, Šmrkić, Gluvović i Bjelogrlić. | G11: ENG30-10632576-n | H11: lekar specijalista | I11: Lekar koji je specijalizirao neku granu medicine. | J11: 1 : Tom prilikom ga je pregledao lekar specijalista i propisao mu odgovarajuću terapiju.
A12: medicine | B12: NULL | C12: ENG30-09793495-n | D12: anesteziolog; lekar anesteziolog | E12: Lekar specijalista koji pacijentu daje anestziju pre tretmana. | F12: 1 : Prilikom operacije nije bilo adekvatne hirurške ekipe, a radilo se i bez anesteziologa. | G12: ENG30-10632576-n | H12: lekar specijalista | I12: Lekar koji je specijalizirao neku granu medicine. | J12: 1 : Tom prilikom ga je pregledao lekar specijalista i propisao mu odgovarajuću terapiju.
A13: medicine | B13: NULL | C13: ENG30-09828760-n | D13: pedijatar; lekar pedijatar; dečiji lekar | E13: Lekar specijalista koji leči decu. | F13: 1 : Prvi simptomi i ono zbog čega roditelji najčešće dolaze kod pedijatra jesu slabije uzimanje obroka i slabije napredovanje njihove bebe. | 2 : R. kaže da dečji lekari sve češće ukazuju kako se javlja i takozvana tipična slika za grip. | G13: ENG30-10632576-n | H13: lekar specijalista | I13: Lekar koji je specijalizirao neku granu medicine. | J13: 1 : Tom prilikom ga je pregledao lekar specijalista i propisao mu odgovarajuću terapiju.
... A123: medicine | B123: NULL | C123: ENG30-00017031-v | D123: hrkati | E123: Bučno disati u toku spavanja | F123: - | G123: ENG30-00001740-v | H123: disati | I123: Udisati vazduh u pluća i izdisati ga. | J123: -
A124: medicine | C124: ENG30-00613473-n | D124: alternativna medicina; komparativna medicina | E124: zdravstvena praksa, pristupi, znanja i verovanja koja se odnose na preparate biljnog, mineralnog ili životinjskog porekla, duhovnu terapiju, kao i manualne tehnike i vežbe koje se primenjuju pojedinačno ili u kombinaciji u svrhu lečenja, dijagnostikovanja i sprečavanja bolesti | F124: - | G124: ENG30-00612160-n | H124: medicina | I124: profesija koja se izučava na medicinskom fakultetu ili sličnim ustanovama a u cilju lečenja i sprečavanja bolesti | J124: -
A125: medicine | C125: ENG30-00612160-n | D125: medicina | E125: profesija koja se izučava na medicinskom fakultetu ili sličnim ustanovama a u cilju lečenja i sprečavanja bolesti | F125: - | G125: ENG30-00610373-n | H125: učena profesija; učeno zanimanje | I125: jedna od tri profesije za koje se po tradiciji smatra da zahtevaju visoku kvalifikaciju i principijelnost | J125: -
A126: medicine | C126: ENG30-00018813-v | D126: ?awaken; ?wake; ?waken; ?rouse; ?wake up; ?arouse | E126: ?cause to become awake or conscious | F126: - | G126: ENG30-00126264-v | H126: izmeniti | I126: Izazvati promenu, transformaciju; učiniti različitim. | J126: -
A127: medicine | C127: ENG30-00022099-v | D127: ?bring to; ?bring back; ?bring round; ?bring around | E127: ?bring back to consciousness | F127: - | G127: ENG30-00018813-v | H127: ?awaken; ?wake; ?waken; ?rouse; ?wake up; ?arouse | I127: ?cause to become awake or conscious | J127: -
A128: medicine | C128: ENG30-00098083-v | D128: ?resuscitate; ?revive | E128: ?cause to regain consciousness | F128: - | G128: ENG30-00022099-v | H128: ?bring to; ?bring back; ?bring round; ?bring around | I128: ?bring back to consciousness | J128: -
A129: medicine | C129: ENG30-00082563-v | D129: izlečiti; isceliti | E129: lečiti i ukloniti simptome bolesti | F129: - | G129: ENG30-00078760-v | H129: obezbediti medicinsku negu | I129: Obebzbediti nekome lečenje. | J129: -
A130: medicine | C130: ENG30-00086077-v | D130: puštati krv; uraditi flebotomiju; flebotomizirati | E130: pustiti krv. | F130: 1 : "U starim vremenima lekar su puštali krv kao deo terapije, najčešće koristeći pijavice" | G130: ENG30-00078760-v | H130: obezbediti medicinsku negu | I130: Obebzbediti nekome lečenje. | J130: -
A131: medicine | C131: ENG30-00832092-n | D131: kardiografija; elektrokardiografija; EKG | E131: Dijagnostička procedura koja prati rad srca. Eletrokardiografijom se korišćenjem aparata elektrokardiograma prate električni impulsi srca i dobija crtež elektrokardiograf - EKG. | F131: - | G131: ENG30-00177127-n | H131: dijagnostička procedura; dijagnostička tehnika | I131: procedura koja se preuzima da bi se došlo do medicinske dijagnoze | J131: -
A132: medicine | C132: ENG30-00832306-n | D132: ehokardiografija | E132: Neinvazivna dijagnostička procedura koja koristi ultrazvuk da snimi strukturu i motoriku srca. | F132: - | G132: ENG30-00177127-n | H132: dijagnostička procedura; dijagnostička tehnika | I132: procedura koja se preuzima da bi se došlo do medicinske dijagnoze | J132: -
A133: medicine | C133: ENG30-00832471-n | D133: ehoencefalografija | E133: Neinvazivna dijagnostička procedura koja koristi ultrazvuk za snimanje strukture mozga; zastarela metoda | F133: - | G133: ENG30-00177127-n | H133: dijagnostička procedura; dijagnostička tehnika | I133: procedura koja se preuzima da bi se došlo do medicinske dijagnoze | J133: -
A134: medicine | C134: ENG30-00876542-n | D134: auskultacija; osluškivanje; oskultacija | E134: osluškivanje zvukova koje stvara organizam (najčešće korišćenjem stetoskopa). | F134: - | G134: ENG30-00882159-n | H134: slušanje | I134: Čin pri kome se pažljivo sluša. | J134: -
A135: medicine | C135: ENG30-00876542-n | D135: auskultacija; osluškivanje; oskultacija | E135: osluškivanje zvukova koje stvara organizam (najčešće korišćenjem stetoskopa). | F135: - | G135: ENG30-00177127-n | H135: dijagnostička procedura; dijagnostička tehnika | I135: procedura koja se preuzima da bi se došlo do medicinske dijagnoze | J135: -
... A420: medicine | C420: ENG30-03060971-a | D420: dijabetički | E420: koji se odnosi ili koji izaziva dijabetes | F420: - | G420: NULL | H420: - | I420: - | J420: -
A421: medicine | B421: % | C421: ENG30-00004227-v | D421: izdahnuti; izdisati | E421: izbaciti vazduh | F421: - | G421: ENG30-00001740-v | H421: disati | I421: Udisati vazduh u pluća i izdisati ga. | J421: -
A422: medicine | B422: % | C422: ENG30-00005041-v | D422: udahnuti; udisati | E422: uvući vazduh | F422: - | G422: ENG30-00001740-v | H422: disati | I422: Udisati vazduh u pluća i izdisati ga. | J422: -
A423: medicine | B423: % | C423: ENG30-14176715-n | D423: fokalna infekcija; žarišna infekcija | E423: bakterijska infekcija ograničena na određeni organ ili region, posebno onaj koji uzrokuje simptome na drugim mestima | F423: - | G423: ENG30-14174549-n | H423: zaraza | I423: Patološko satnje do koga dolazi kada patološki mikroorganizmi napadnu telo. | J423: -
A424: medicine | B424: % | C424: ENG30-00097029-v | D424: crtati | E424: izazvati lokalizaciju u jednoj tački | F424: - | G424: ENG30-02509919-v | H424: lokalizovati | I424: šta na određeno područje ograničiti | J424: -
A425: medicine | B425: % | C425: ENG30-00142361-n | D425: lekarski pregled; medicinski pregled; pregled | E425: temeljni pregled; uključuje različite testove u zavisnosti od starosti i pola i zdravlja osobe | F425: - | G425: ENG30-00635850-n | H425: pregled; pregledanje | I425: Čin detaljnog pregledanja (kao pri traženju grešaka). | J425: -
A426: medicine | B426: % | C426: ENG30-00359511-v | D426: udaviti se; ugušiti se | E426: ugušiti se; umreti od nedostatka kiseonika | F426: - | G426: ENG30-00358431-v | H426: umreti; izdahnuti; uginuti; crknuti; preminuti; nestati | I426: Napustiti fizički život i izgubiti sve telesne funkcije i atribute koji se neophodni da bi se održao život. | J426: -
A427: medicine | B427: % | C427: ENG30-00928232-v | D427: pokazati; pokazivati; ukazati; ukazivati | E427: ukazati na neophodnost kakvog zahvata (u medicini) | F427: - | G427: ENG30-00831651-v | H427: informisati | I427: Preneti nekome znanje o nekoj činjenici, stanju stvari ili događaju. | J427: -
A428: medicine | B428: % | C428: ENG30-03957420-n | D428: gips | E428: ljepljiva traka koja se koristi za oblaganje rana | F428: - | G428: ENG30-02680337-n | H428: lepljiva traka | I428: traka prevučena lepkom | J428: -
A429: medicine | B429: % | C429: ENG30-04013729-n | D429: proteza | E429: korektivni uređaj koji se sastoji od zamene za deo tela | F429: - | G429: ENG30-03111899-n | H429: sredstvo za ublažavanje bolova | I429: Naprava za lečenje povreda ili bolesti. | J429: -
A430: medicine | B430: % | C430: ENG30-04376876-n | D430: špric | E430: medicinski instrument koji se koristi za ubrizgavanje ili izvlačenje tečnosti | F430: - | G430: ENG30-03739693-n | H430: medicinski instrument | I430: Instrument koji se koristi u bavljenju medicinom. | J430: 1 : Pomoć EU u lekovima i medicinskim instrumentima, za koje je EU dala 20 miliona evra.
A431: medicine | B431: % | C431: ENG30-08112630-n | D431: lekarska profesija; zdravstvo | E431: zbir pojedinaca čiji rad pomaže očuvanju zdravlja njihovih klijenata | F431: - | G431: ENG30-08112096-n | H431: profesionalna zajednica | I431: Telo luxdi koji se bave nekom učenom profesijom. | J431: -
A432: medicine | B432: % | C432: ENG30-00022316-v | D432: smiriti | E432: učiniti mirnim ili tihim pomoću sedativa | F432: - | G432: ENG30-00019448-v | H432: pogoditi; pogađati | I432: Imati uticaja na nešto, fizički uticati | J432: -
... A498: medicine | B498: 3 | C498: ENG30-00078760-v | D498: obezbediti medicinsku negu | E498: Obebzbediti nekome lečenje. | F498: - | G498: NULL | H498: - | I498: - | J498: -

Sheet engleski
A1: domain | B1: BCS | C1: ID | D1: literals | E1: def | F1: usage | G1: hypernymID | H1: hypernym_literals | I1: hypernym_def | J1: hypernym_usage | K1: Prevod literala | L1: Prevod def
A2: medicine | C2: ENG30-00005526-v | D2: pant; puff; gasp; heave | E2: breathe noisily, as when one is exhausted | F2: 1 : The runners reached the finish line, panting heavily | G2: ENG30-00007012-v | H2: blow | I2: exhale hard | J2: 1 : blow on the soup to cool it down | K2: =ifna(VLOOKUP(C2,srpski!C:D,2,false),"") | L2: =ifna(VLOOKUP(C2,srpski!C:E,3,false),"")
A3: medicine | C3: ENG30-00006523-v | D3: snort | E3: make a snorting sound by exhaling hard | F3: 1 : The critic snorted contemtuously | G3: ENG30-00004227-v | H3: exhale; expire; breathe out | I3: expel air | J3: 1 : Exhale when you lift the weight | K3: =ifna(VLOOKUP(C3,srpski!C:D,2,false),"") | L3: =ifna(VLOOKUP(C3,srpski!C:E,3,false),"")
A4: medicine | C4: ENG30-00006697-v | D4: wheeze | E4: breathe with difficulty | F4: - | G4: ENG30-00001740-v | H4: breathe; take a breath; respire; suspire | I4: draw air into, and expel out of, the lungs | J4: 1 : The patient is respiring | 2 : I can breathe better when the air is clean | K4: =ifna(VLOOKUP(C4,srpski!C:D,2,false),"") | L4: =ifna(VLOOKUP(C4,srpski!C:E,3,false),"")
A5: medicine | C5: ENG30-00006802-v | D5: puff; huff; chuff | E5: blow hard and loudly | F5: 1 : he huffed and puffed as he made his way up the mountain | G5: ENG30-00007012-v | H5: blow | I5: exhale hard | J5: 1 : blow on the soup to cool it down | K5: =ifna(VLOOKUP(C5,srpski!C:D,2,false),"") | L5: =ifna(VLOOKUP(C5,srpski!C:E,3,false),"")
A6: medicine | C6: ENG30-00007012-v | D6: blow | E6: exhale hard | F6: 1 : blow on the soup to cool it down | G6: ENG30-00004227-v | H6: exhale; expire; breathe out | I6: expel air | J6: 1 : Exhale when you lift the weight | K6: =ifna(VLOOKUP(C6,srpski!C:D,2,false),"") | L6: =ifna(VLOOKUP(C6,srpski!C:E,3,false),"")
A7: medicine | C7: ENG30-00007328-v | D7: yawn | E7: utter a yawn, as from lack of oxygen or when one is tired | F7: 1 : The child yawned during the long performance | G7: ENG30-00001740-v | H7: breathe; take a breath; respire; suspire | I7: draw air into, and expel out of, the lungs | J7: 1 : The patient is respiring | 2 : I can breathe better when the air is clean | K7: =ifna(VLOOKUP(C7,srpski!C:D,2,false),"") | L7: =ifna(VLOOKUP(C7,srpski!C:E,3,false),"")
A8: medicine | C8: ENG30-00007549-v | D8: sniff; sniffle | E8: inhale audibly through the nose | F8: 1 : the sick student was sniffling in the back row | G8: ENG30-00005041-v | H8: inhale; inspire; breathe in | I8: draw in (air) | J8: 1 : The lung cancer patient cannot inspire air very well | 2 : Inhale deeply | 3 : inhale the fresh mountain air | 4 : The patient has trouble inspiring | K8: =ifna(VLOOKUP(C8,srpski!C:D,2,false),"") | L8: =ifna(VLOOKUP(C8,srpski!C:E,3,false),"")
A9: medicine | C9: ENG30-00017031-v | D9: snore; saw wood; saw logs | E9: breathe noisily during one`s sleep | F9: 1 : she complained that her husband snores | G9: ENG30-00001740-v | H9: breathe; take a breath; respire; suspire | I9: draw air into, and expel out of, the lungs | J9: 1 : The patient is respiring | 2 : I can breathe better when the air is clean | K9: =ifna(VLOOKUP(C9,srpski!C:D,2,false),"") -> hrkati | L9: =ifna(VLOOKUP(C9,srpski!C:E,3,false),"") -> Bučno disati u toku spavanja
A10: medicine | C10: ENG30-00018813-v | D10: awaken; wake; waken; rouse; wake up; arouse | E10: cause to become awake or conscious | F10: 1 : Please wake me at 6 AM. | 2 : He was roused by the drunken men in the street | G10: ENG30-00126264-v | H10: change; alter; modify | I10: cause to change; make different; cause a transformation | J10: 1 : The discussion has changed my thinking about the issue | 2 : The advent of the automobile may have altered the growth pattern of the city | K10: =ifna(VLOOKUP(C10,srpski!C:D,2,false),"") -> ?awaken; ?wake; ?waken; ?rouse; ?wake up; ?arouse | L10: =ifna(VLOOKUP(C10,srpski!C:E,3,false),"") -> ?cause to become awake or conscious
A11: medicine | C11: ENG30-00019182-v | D11: reawaken | E11: awaken once again | F11: - | G11: ENG30-00018813-v | H11: awaken; wake; waken; rouse; wake up; arouse | I11: cause to become awake or conscious | J11: 1 : Please wake me at 6 AM. | 2 : He was roused by the drunken men in the street | K11: =ifna(VLOOKUP(C11,srpski!C:D,2,false),"") | L11: =ifna(VLOOKUP(C11,srpski!C:E,3,false),"")
A12: medicine | C12: ENG30-00019273-v | D12: cause to sleep | E12: make fall asleep | F12: 1 : The soft music caused us to to fall asleep | G12: ENG30-00126264-v | H12: change; alter; modify | I12: cause to change; make different; cause a transformation | J12: 1 : The discussion has changed my thinking about the issue | 2 : The advent of the automobile may have altered the growth pattern of the city | K12: =ifna(VLOOKUP(C12,srpski!C:D,2,false),"") | L12: =ifna(VLOOKUP(C12,srpski!C:E,3,false),"")
A13: medicine | C13: ENG30-00020671-v | D13: hypnotize; hypnotise; mesmerize; mesmerise | E13: induce hypnosis in | F13: - | G13: ENG30-00022316-v | H13: sedate; calm; tranquilize; tranquillize; tranquillise | I13: cause to be calm or quiet as by administering a sedative to | J13: 1 : The patient must be sedated before the operation | K13: =ifna(VLOOKUP(C13,srpski!C:D,2,false),"") | L13: =ifna(VLOOKUP(C13,srpski!C:E,3,false),"")
... A2303: medicine | C2303: ENG30-14496563-n | D2303: spotlessness; immaculateness | E2303: the state of being spotlessly clean | F2303: - | G2303: ENG30-14496193-n | H2303: cleanness | I2303: the state of being clean; without dirt or other impurities | J2303: - | K2303: =ifna(VLOOKUP(C2303,srpski!C:D,2,false),"") | L2303: =ifna(VLOOKUP(C2303,srpski!C:E,3,false),"")
A2304: medicine | B2304: $ | C2304: ENG30-07537973-n | D2304: demoralization; demoralisation | E2304: depression resulting from an undermining of your morale | F2304: - | G2304: ENG30-07537485-n | H2304: depression | I2304: sad feelings of gloom and inadequacy | J2304: - | K2304: =ifna(VLOOKUP(C2304,srpski!C:D,2,false),"") -> demoralizacija | L2304: =ifna(VLOOKUP(C2304,srpski!C:E,3,false),"") -> depresija koja proizlazi iz podrivanja morala
A2305: medicine | B2305: $ | C2305: ENG30-14496193-n | D2305: cleanness | E2305: the state of being clean; without dirt or other impurities | F2305: - | G2305: ENG30-14494716-n | H2305: sanitary condition | I2305: the state of sanitation (clean or dirty) | J2305: - | K2305: =ifna(VLOOKUP(C2305,srpski!C:D,2,false),"") -> čistoća | L2305: =ifna(VLOOKUP(C2305,srpski!C:E,3,false),"") -> Stanje čiste osobe; bez prljavštine ili drugih nečistoća.
A2306: medicine | B2306: $ | C2306: ENG30-14494716-n | D2306: sanitary condition | E2306: the state of sanitation (clean or dirty) | F2306: - | G2306: ENG30-13920835-n | H2306: condition; status | I2306: a state at a particular time | J2306: 1 : the current status of the arms negotiations | 2 : a condition (or state) of disrepair | K2306: =ifna(VLOOKUP(C2306,srpski!C:D,2,false),"") -> higijenski uslovi; sanitarni uslovi | L2306: =ifna(VLOOKUP(C2306,srpski!C:E,3,false),"") -> Zdravstveni uslovi (čisti ili prljavi).
A2307: medicine | B2307: $ | C2307: ENG30-14182697-n | D2307: focus; focal point; nidus | E2307: a central point or locus of an infection in an organism | F2307: 1 : the focus of infection | G2307: ENG30-08620061-n | H2307: point | I2307: the precise location of something; a spatially limited location | J2307: 1 : she walked to a point where she could survey the whole street | K2307: =ifna(VLOOKUP(C2307,srpski!C:D,2,false),"") -> žiža; žarište | L2307: =ifna(VLOOKUP(C2307,srpski!C:E,3,false),"") -> Središnja tačka ili mesto rasta bakterija u organizmu.
A2308: medicine | B2308: $ | C2308: ENG30-14292090-n | D2308: fracture; break | E2308: breaking of hard tissue such as bone | F2308: 1 : the break seems to have been caused by a fall | 2 : it was a nasty fracture | G2308: ENG30-14285662-n | H2308: injury; hurt; harm; trauma | I2308: any physical damage to the body caused by violence or accident or fracture etc. | J2308: - | K2308: =ifna(VLOOKUP(C2308,srpski!C:D,2,false),"") -> prelom; fraktura | L2308: =ifna(VLOOKUP(C2308,srpski!C:E,3,false),"") -> Prelom tvrdog tkiva poput kosti.
A2309: medicine | B2309: $ | C2309: ENG30-14379501-n | D2309: sanity; saneness | E2309: normal or sound powers of mind | F2309: - | G2309: ENG30-14379130-n | H2309: mental health | I2309: the psychological state of someone who is functioning at a satisfactory level of emotional and behavioral adjustment | J2309: - | K2309: =ifna(VLOOKUP(C2309,srpski!C:D,2,false),"") -> normalnost | L2309: =ifna(VLOOKUP(C2309,srpski!C:E,3,false),"") -> Normalne ili zdrave umne moći.
A2310: medicine | B2310: $ | C2310: ENG30-14055408-n | D2310: ailment; complaint; ill | E2310: an often persistent bodily disorder or disease; a cause for complaining | F2310: - | G2310: ENG30-14052403-n | H2310: disorder; upset | I2310: condition in which there is a disturbance of normal functioning | J2310: 1 : everyone gets stomach upsets from time to time | 2 : the doctor prescribed some medicine for the disorder | K2310: =ifna(VLOOKUP(C2310,srpski!C:D,2,false),"") -> tegoba; boljka | L2310: =ifna(VLOOKUP(C2310,srpski!C:E,3,false),"") -> lak ali često stalan telesni poremećaj ili bolest
A2311: medicine | B2311: $ | C2311: ENG30-14174549-n | D2311: infection | E2311: the pathological state resulting from the invasion of the body by pathogenic microorganisms | F2311: - | G2311: ENG30-14052046-n | H2311: ill health; unhealthiness; health problem | I2311: a state in which you are unable to function normally and without pain | J2311: - | K2311: =ifna(VLOOKUP(C2311,srpski!C:D,2,false),"") -> zaraza | L2311: =ifna(VLOOKUP(C2311,srpski!C:E,3,false),"") -> Patološko satnje do koga dolazi kada patološki mikroorganizmi napadnu telo.
A2312: medicine | B2312: $ | C2312: ENG30-14066203-n | D2312: collapse | E2312: an abrupt failure of function or health | F2312: - | G2312: ENG30-14061805-n | H2312: illness; unwellness; malady; sickness | I2312: impairment of normal physiological function affecting part or all of an organism | J2312: - | K2312: =ifna(VLOOKUP(C2312,srpski!C:D,2,false),"") -> kolaps; klonulost; malaksalost | L2312: =ifna(VLOOKUP(C2312,srpski!C:E,3,false),"") -> naglo posustajanje funkcije ili zdravlja
A2313: medicine | B2313: $ | C2313: ENG30-10366966-n | D2313: nurse | E2313: one skilled in caring for young children or the sick (usually under the supervision of a physician) | F2313: - | G2313: ENG30-10165109-n | H2313: health professional; health care provider; caregiver | I2313: a person who helps in identifying or preventing or treating illness or disability | J2313: - | K2313: =ifna(VLOOKUP(C2313,srpski!C:D,2,false),"") -> sestra; medicinska sestra; bolničarka | L2313: =ifna(VLOOKUP(C2313,srpski!C:E,3,false),"") -> Osoba obučena za brigu o bolesnicima (obično pod nadzorom lekara).
A2314: medicine | B2314: $ | C2314: ENG30-10004282-n | D2314: dentist; tooth doctor; dental practitioner | E2314: a person qualified to practice dentistry | F2314: - | G2314: ENG30-10305802-n | H2314: medical practitioner; medical man | I2314: someone who practices medicine | J2314: - | K2314: =ifna(VLOOKUP(C2314,srpski!C:D,2,false),"") -> stomatolog; zubar; dentista | L2314: =ifna(VLOOKUP(C2314,srpski!C:E,3,false),"") -> osoba kvalifikovana da se bavi stomatologijom
A2315: medicine | B2315: $ | C2315: ENG30-00089324-v | D2315: disinfect | E2315: destroy microorganisms or pathogens by cleansing | F2315: 1 : disinfect a wound | G2315: ENG30-01532589-v | H2315: clean; make clean | I2315: make clean by removing dirt, filth, or unwanted substances from | J2315: 1 : The dentist cleaned my teeth | 2 : Clean the stove! | K2315: =ifna(VLOOKUP(C2315,srpski!C:D,2,false),"") -> dezinfikovati | L2315: =ifna(VLOOKUP(C2315,srpski!C:E,3,false),"") -> Uništiti mikroorganizme čišćenjem na poseban način.
... A2384: medicine | B2384: * | C2384: ENG30-00658082-n | D2384: treatment | E2384: care by procedures or applications that are intended to relieve illness or injury | F2384: - | G2384: ENG30-00654885-n | H2384: care; attention; aid; tending | I2384: the work of caring for or attending to someone or something | J2384: 1 : the old car needed constant attention | 2 : no medical care was required | K2384: =ifna(VLOOKUP(C2384,srpski!C:D,2,false),"") -> tretman; lečenje | L2384: =ifna(VLOOKUP(C2384,srpski!C:E,3,false),"") -> Nega postupcima ili primenama čiji je cilj olakšanje bolesti ili povrede.
